stock_super/__init__.py
stock_super/config.py
stock_super/data_fetcher.py
stock_super/data_get.py
stock_super/data_processor.py
stock_super/utils.py
stock_super-0.0.1.dist-info/LICENSE
stock_super-0.0.1.dist-info/METADATA
stock_super-0.0.1.dist-info/WHEEL
stock_super-0.0.1.dist-info/entry_points.txt
stock_super-0.0.1.dist-info/top_level.txt
stock_super-0.0.1.dist-info/RECORD
