Metadata-Version: 2.1
Name: stock_super
Version: 0.0.1
Summary: 简单实现获取股票数据
Home-page: 
Author: 冯帅
Author-email: ucjmhfeng@126.com
Classifier: Programming Language :: Python :: 3
Classifier: License :: OSI Approved :: MIT License
Classifier: Operating System :: OS Independent
Requires-Python: >=3.10
License-File: LICENSE
Requires-Dist: requests>=2.25.1
Requires-Dist: pandas>=1.1.0
